README.rst
setup.py
omgl/__init__.py
omgl/debug.py
omgl/dtypes.py
omgl/object.py
omgl/proxy.py
omgl/version.py
omgl.egg-info/PKG-INFO
omgl.egg-info/SOURCES.txt
omgl.egg-info/dependency_links.txt
omgl.egg-info/requires.txt
omgl.egg-info/top_level.txt
omgl/buffer/__init__.py
omgl/buffer/buffer.py
omgl/buffer/buffer_pointer.py
omgl/buffer/vertex_array.py
omgl/mesh/__init__.py
omgl/mesh/mesh.py
omgl/pipeline/__init__.py
omgl/pipeline/pipeline.py
omgl/shader/__init__.py
omgl/shader/enumerations.py
omgl/shader/program.py
omgl/shader/shader.py
omgl/shader/variables.py
omgl/texture/__init__.py
omgl/texture/texture.py