Metadata-Version: 1.1
Name: omgl
Version: 0.0.2
Summary: Pythonic OpenGL Bindings
Home-page: https://github.com/adamlwgriffiths/omgl
Author: Adam Griffiths
Author-email: UNKNOWN
License: BSD
Platform: any
Classifier: Natural Language :: English
Classifier: Intended Audience :: Developers
Classifier: Operating System :: MacOS :: MacOS X
Classifier: Operating System :: Microsoft :: Windows
Classifier: Operating System :: POSIX
Classifier: Programming Language :: Python
Classifier: License :: OSI Approved :: BSD License
Classifier: Topic :: Multimedia :: Graphics
Classifier: Topic :: Software Development :: Libraries
Classifier: Topic :: Software Development :: Libraries :: Python Modules
